pyusbmodule-0.1.7.dist-info/METADATA
pyusbmodule-0.1.7.dist-info/RECORD
pyusbmodule-0.1.7.dist-info/WHEEL
pyusbmodule-0.1.7.dist-info/top_level.txt
usbmodule/__init__.py
usbmodule/r4i4d.py
