Metadata-Version: 2.1
Name: pyusbmodule
Version: 0.1.7
Summary: Python interface to expansion modules via USB-Modbus/UART connection
Home-page: https://github.com/laigui/pyusbmodule.git
Author: Mike Qin
Author-email: laigui@gmail.com
License: UNKNOWN
Project-URL: Bug Reports, https://github.com/laigui/pyusbmodule/issues
Project-URL: Source, https://github.com/laigui/pyusbmodule/
Keywords: usb modbus serail
Platform: UNKNOWN
Classifier: Development Status :: 3 - Alpha
Classifier: Intended Audience :: Developers
Classifier: Topic :: Software Development :: Libraries :: Python Modules
Classifier: Topic :: System :: Hardware :: Hardware Drivers
Classifier: License :: OSI Approved :: Apache Software License
Classifier: Programming Language :: Python :: 3
Classifier: Programming Language :: Python :: 3.4
Classifier: Programming Language :: Python :: 3.5
Classifier: Programming Language :: Python :: 3.6
Requires-Python: >=3
Provides-Extra: dev
Provides-Extra: test
Requires-Dist: minimalmodbus
Provides-Extra: dev
Requires-Dist: check-manifest; extra == 'dev'
Provides-Extra: test
Requires-Dist: coverage; extra == 'test'
